{
  "pnls": {
    "PnL (total)": 8229.4,
    "PnL% (total)": 8.229399999999993,
    "Max Winner": 494.89,
    "Avg Winner": 494.6054545454545,
    "Min Winner": 494.31,
    "Min Loser": -33.16,
    "Avg Loser": -323.7032,
    "Max Loser": -356.69,
    "Expectancy": 141.8862068965517,
    "Win Rate": 0.5689655172413793
  },
  "general": {
    "Long Ratio": "0.50",
    "Total trades": 0,
    "Sharpe ratio": 0.0,
    "Profit factor": 0.0,
    "Max drawdown": 0.0
  },
  "rejected_signals_count": 338
}